prophecy_deploy_cli_executable/__init__.py
prophecy_deploy_cli_executable-1.0.0.dist-info/METADATA
prophecy_deploy_cli_executable-1.0.0.dist-info/WHEEL
prophecy_deploy_cli_executable-1.0.0.dist-info/top_level.txt
prophecy_deploy_cli_executable-1.0.0.dist-info/RECORD
