Metadata-Version: 2.4
Name: prophecy-deploy-cli-executable
Version: 1.0.0
Summary: Prophecy Deploy CLI Main Executable (JPMC) - Placeholder
Author-email: Prophecy <support@prophecy.io>
License: Proprietary
Project-URL: Homepage, https://prophecy.io
Project-URL: Repository, https://github.com/prophecy-io/prophecy-deploy-cli-binary
Keywords: prophecy,deploy,cli,binary,executable,placeholder
Classifier: Programming Language :: Python :: 3
Classifier: License :: Other/Proprietary License
Classifier: Operating System :: POSIX :: Linux
Requires-Python: >=3.8
